ollama_think/__init__.py
ollama_think/client.py
ollama_think/config.py
ollama_think/config.yaml
ollama_think/py.typed
ollama_think/stream_parser.py
ollama_think/thinking_hacks.py
ollama_think/thinkresponse.py
ollama_think-0.1.10.dist-info/METADATA
ollama_think-0.1.10.dist-info/WHEEL
ollama_think-0.1.10.dist-info/licenses/LICENSE
ollama_think-0.1.10.dist-info/RECORD
