Metadata-Version: 2.4
Name: ollama-think
Version: 0.1.10
Summary: A light wrapper around ollama-python that introduces caching, syntax sugar and increased `think` compatibility
Project-URL: Homepage, https://github.com/rhiza-fr/ollama-think
Project-URL: Bug Tracker, https://github.com/rhiza-fr/ollama-think/issues
Author-email: Chris Kilner <chris@rhiza.fr>
License-File: LICENSE
Keywords: AI,LLM,cogito,compatibility,granite,ollama,phi4-mini-reasoning,phi4-reasoning,think
Classifier: Development Status :: 4 - Beta
Classifier: Intended Audience :: Developers
Classifier: License :: OSI Approved :: MIT License
Classifier: Programming Language :: Python :: 3
Classifier: Programming Language :: Python :: 3.12
Classifier: Topic :: Scientific/Engineering :: Artificial Intelligence
Classifier: Topic :: Software Development :: Libraries :: Python Modules
Requires-Python: >=3.9
Requires-Dist: diskcache>=5.6
Requires-Dist: ollama>=0.5.3
Requires-Dist: pyyaml>=6.0
Provides-Extra: dev
Requires-Dist: pytest-asyncio>=1.1.0; extra == 'dev'
Requires-Dist: pytest-cov>=6.2.0; extra == 'dev'
Requires-Dist: pytest-mock>=3.14.1; extra == 'dev'
Requires-Dist: pytest>=8.4.0; extra == 'dev'
Requires-Dist: ruff>=0.11.13; extra == 'dev'
